og/__init__.py
og/timer/Datetime.py
og/timer/Timer.py
og/timer/__init__.py
oangia-0.0.3.dist-info/METADATA
oangia-0.0.3.dist-info/WHEEL
oangia-0.0.3.dist-info/top_level.txt
oangia-0.0.3.dist-info/RECORD
