Metadata-Version: 2.1
Name: oangia
Version: 0.0.3
Summary: My private package
Author: OG
Author-email: blogphp.biz@gmail.com
License: UNKNOWN
Keywords: python,utils
Platform: UNKNOWN
Classifier: Development Status :: 3 - Alpha
Classifier: Intended Audience :: Education
Classifier: Programming Language :: Python :: 3
Classifier: Operating System :: MacOS :: MacOS X
Classifier: Operating System :: Microsoft :: Windows
Requires-Dist: numpy
Requires-Dist: pandas
